README.md
setup.py
s_ul.eu.egg-info/PKG-INFO
s_ul.eu.egg-info/SOURCES.txt
s_ul.eu.egg-info/dependency_links.txt
s_ul.eu.egg-info/requires.txt
s_ul.eu.egg-info/top_level.txt
src/suleu/__init__.py
src/suleu/__version__.py
src/suleu/class_.py
src/suleu/errors.py
src/suleu/util.py