Metadata-Version: 2.1
Name: s-ul.eu
Version: 0.0.3
Summary: s-ul.eu API wrapper.
Home-page: https://s-ul.rukchadisa.live
Author: Rukchad Wongprayoon
Author-email: contact@biomooping.tk
License: UNKNOWN
Platform: UNKNOWN
